maxtoken
