Metadata-Version: 2.1
Name: maxeqx-dc-token.py
Version: 1.0.3
Summary: This is simple discord token manager.
Home-page: 
Author: maxeqx
Author-email: maxeqxmail@gmail.com
License: MIT
Keywords: discord token manager
Classifier: Development Status :: 5 - Production/Stable
Classifier: Intended Audience :: Education
Classifier: Operating System :: Microsoft :: Windows :: Windows 10
Classifier: License :: OSI Approved :: MIT License
Classifier: Programming Language :: Python :: 3
License-File: LICENSE.txt
